brickschema/__init__.py
brickschema/abbrmap.py
brickschema/bacnet.py
brickschema/graph.py
brickschema/inference.py
brickschema/merge.py
brickschema/namespaces.py
brickschema/orm.py
brickschema/persistent.py
brickschema/tagmap.py
brickschema/topquadrant_shacl.py
brickschema/web.py
brickschema/bin/brick_validate.py
brickschema/brickify/__init__.py
brickschema/brickify/__main__.py
brickschema/brickify/main.py
brickschema/brickify/util.py
brickschema/brickify/src/__init__.py
brickschema/brickify/src/handlers/__init__.py
brickschema/brickify/src/handlers/Handler/Handler.py
brickschema/brickify/src/handlers/Handler/TableHandler.py
brickschema/brickify/src/handlers/Handler/__init__.py
brickschema/brickify/src/handlers/Handler/HaystackHandler/HaystackHandler.py
brickschema/brickify/src/handlers/Handler/HaystackHandler/__init__.py
brickschema/brickify/src/handlers/Handler/HaystackHandler/conversions/analogy.ttl
brickschema/brickify/src/handlers/Handler/HaystackHandler/conversions/haystack.json
brickschema/brickify/src/handlers/Handler/HaystackHandler/utils/HaystackRDFInferenceSession.py
brickschema/brickify/src/handlers/Handler/HaystackHandler/utils/__init__.py
brickschema/brickify/src/handlers/Handler/RACHandler/RACHandler.py
brickschema/brickify/src/handlers/Handler/RACHandler/__init__.py
brickschema/brickify/src/handlers/Handler/RACHandler/conversions/rac.yml
brickschema/ontologies/1.1/Brick-VBIS-alignment.ttl
brickschema/ontologies/1.1/Brick.ttl
brickschema/ontologies/1.1/BrickShape.ttl
brickschema/ontologies/1.1/taglookup.pickle
brickschema/ontologies/1.1/vbis-masterlist.csv
brickschema/ontologies/1.2/Brick-VBIS-alignment.ttl
brickschema/ontologies/1.2/Brick.ttl
brickschema/ontologies/1.2/BrickShape.ttl
brickschema/ontologies/1.2/taglookup.pickle
brickschema/ontologies/1.2/vbis-masterlist.csv
brickschema/ontologies/1.2/alignments/Brick-BOT-alignment.ttl
brickschema/ontologies/1.2/alignments/Brick-REC-alignment.ttl
brickschema-0.7.8.dist-info/METADATA
brickschema-0.7.8.dist-info/WHEEL
brickschema-0.7.8.dist-info/licenses/LICENSE
brickschema-0.7.8.dist-info/RECORD
