Metadata-Version: 2.4
Name: brickschema
Version: 0.7.8
Summary: A library for working with the Brick ontology for buildings (brickschema.org)
Author-email: Gabe Fierro <gtfierro@mines.edu>
License-Expression: BSD-3-Clause
License-File: LICENSE
Requires-Python: <4.0,>=3.10
Requires-Dist: importlib-resources>=6.5.2
Requires-Dist: owlrl>=7.1.3
Requires-Dist: pyontoenv>=0.3.0
Requires-Dist: pyshacl>=0.30.1
Requires-Dist: rdflib>=7.1.4
Requires-Dist: requests>=2.32.4
Provides-Extra: allegro
Requires-Dist: docker>=7.1.0; extra == 'allegro'
Provides-Extra: bacnet
Requires-Dist: bac0>=2025.6.10; extra == 'bacnet'
Provides-Extra: brickify
Requires-Dist: click-spinner>=0.1.10; extra == 'brickify'
Requires-Dist: jinja2>=3.1.6; extra == 'brickify'
Requires-Dist: pyyaml>=6.0.2; extra == 'brickify'
Requires-Dist: tabulate>=0.9.0; extra == 'brickify'
Requires-Dist: typer>=0.16.0; extra == 'brickify'
Requires-Dist: xlrd>=2.0.2; extra == 'brickify'
Provides-Extra: merge
Requires-Dist: colorama>=0.4.6; extra == 'merge'
Requires-Dist: dedupe>=3.0.3; extra == 'merge'
Provides-Extra: networkx
Requires-Dist: networkx>=3.0; extra == 'networkx'
Provides-Extra: orm
Requires-Dist: sqlalchemy>=2.0.41; extra == 'orm'
Provides-Extra: persistence
Requires-Dist: alembic>=1.16.4; extra == 'persistence'
Requires-Dist: brickschema-rdflib-sqlalchemy>=0.6.1; extra == 'persistence'
Requires-Dist: six>=1.17.0; extra == 'persistence'
Requires-Dist: sqlalchemy>=2.0.41; extra == 'persistence'
Provides-Extra: reasonable
Requires-Dist: reasonable>=0.2.6; extra == 'reasonable'
Provides-Extra: topquadrant
Requires-Dist: brick-tq-shacl>=0.4.0a8; extra == 'topquadrant'
Provides-Extra: web
Requires-Dist: flask>=3.1.1; extra == 'web'
